{
  "project_info": {
    "project_number": "290443008463",
    "project_id": "safearound-d39a0",
    "storage_bucket": "safearound-d39a0.firebasestorage.app"
  },
  "client": [
    {
      "client_info": {
        "mobilesdk_app_id": "1:290443008463:android:945bef046bc1ecdb2d9aba",
        "android_client_info": {
          "package_name": "com.safearound.app"
        }
      },
      "oauth_client": [],
      "api_key": [
        {
          "current_key": "AIzaSyDQdmquUZFArDCbBR9KTCyfB5xai02wBuo"
        }
      ],
      "services": {
        "appinvite_service": {
          "other_platform_oauth_client": []
        }
      }
    }
  ],
  "configuration_version": "1"
}